[
    { "name": "High Flyer", "image": "https://cloudcdn.owcontent.com/games/pragmaticplay/2201.jpg?221746438614000" },
    { "name": "OnwinX", "image": "https://cloudcdn.owcontent.com/games/smartsoft/JetX.gif?221690317704000" },
    { "name": "Plinko Show", "image": "https://cloudcdn.owcontent.com/games/ninjagaming/plinko-show.png?221746170865000" },
    { "name": "Auto Roulette", "image": "https://cloudcdn.owcontent.com/games/originals/018f864a-3ad0-7fd9-8cc3-819706e30403.png?221735054210000" },
    { "name": "Crash", "image": "https://cloudcdn.owcontent.com/games/originals/018f6c72-c3a4-7cdb-8107-cfb3e12dc172.png?221735054230000" },
    { "name": "Hilo", "image": "https://cloudcdn.owcontent.com/games/originals/019026bc-69fd-74d6-b94b-878717cfb252.png?221735054241000" },
    { "name": "Dice", "image": "https://cloudcdn.owcontent.com/games/originals/01907275-8a48-7708-bd74-4d42903f2b29.png?221735054248000" },
    { "name": "Plinko", "image": "https://cloudcdn.owcontent.com/games/originals/01910768-e8be-7e3d-9a6b-0bfe172bd923.png?221735054256000" },
    { "name": "Mines", "image": "https://cloudcdn.owcontent.com/games/originals/01912caa-7e0b-76fd-b525-fd97d129e4b7.png?221735054263000" },
    { "name": "Limbo", "image": "https://cloudcdn.owcontent.com/games/originals/01927a78-e69e-74e4-921a-7c1834b2d1dc.png?221735054271000" },
    { "name": "Crash X", "image": "https://cloudcdn.owcontent.com/games/turbogames/crash.png?221746631283000" },
    { "name": "Aero", "image": "https://cloudcdn.owcontent.com/games/turbogames/aero.webp?221746631283000" },
    { "name": "Crash X Football Edition", "image": "https://cloudcdn.owcontent.com/games/turbogames/crashfootball.png?221746631283000" },
    { "name": "Zeppelin", "image": "https://cloudcdn.owcontent.com/games/betsolutions/zeppelin.jpg?221596007900000" },
    { "name": "Skyward", "image": "https://cloudcdn.owcontent.com/games/bgtv/27.png?22NaN" },
    { "name": "Spaceman", "image": "https://cloudcdn.owcontent.com/games/pragmaticplay/1301.gif?221658764834000" },
    { "name": "HelicopterX", "image": "https://cloudcdn.owcontent.com/games/smartsoft/HelicopterX.webp?221708503871000" },
    { "name": "Big Bass Crash", "image": "https://cloudcdn.owcontent.com/games/pragmaticplay/1320.png?221695829283000" },
    { "name": "Avionix Crash", "image": "https://cloudcdn.owcontent.com/games/studio21/s21.crash.avionix.webp?221726221977000" },
    { "name": "Bigiboy Crash", "image": "https://cloudcdn.owcontent.com/games/falcongaming/bigiboy.jpg?221711365416000" },
    { "name": "MAGNIFY MAN", "image": "https://cloudcdn.owcontent.com/games/fugaso/97.jpg?221667297671000" },
    { "name": "Raptor", "image": "https://cloudcdn.owcontent.com/games/falcongaming/raptor.gif?221656834108000" },
    { "name": "submarine", "image": "https://cloudcdn.owcontent.com/games/falcongaming/submarine.gif?221695295949000" },
    { "name": "Football X", "image": "https://cloudcdn.owcontent.com/games/smartsoft/FootballX.png?221668627750000" },
    { "name": "Genies Bonanza", "image": "https://cloudcdn.owcontent.com/games/smartsoft/GeniesBonanza.png?221744025692000" },
    { "name": "JetX3", "image": "https://cloudcdn.owcontent.com/games/smartsoft/JetX3.jpg?221631526943000" },
    { "name": "Balloon", "image": "https://cloudcdn.owcontent.com/games/smartsoft/Balloon.jpg?221631526910000" },
    { "name": "Multi Hot 5", "image": "https://cloudcdn.owcontent.com/games/smartsoft/MultiHot5.jpg?221665752986000" },
    { "name": "PlinkoX", "image": "https://cloudcdn.owcontent.com/games/smartsoft/plinkox.jpg?221656667433000" },
    { "name": "Cappadocia", "image": "https://cloudcdn.owcontent.com/games/smartsoft/Cappadocia.jpg?221630054585000" },
    { "name": "Vortex", "image": "https://cloudcdn.owcontent.com/games//turbogames/vortex.png?221746631283000" },
    { "name": "Fruit Towers", "image": "https://cloudcdn.owcontent.com/games/turbogames/fruittowers.png?221746631283000" },
    { "name": "Turbo Plinko", "image": "https://cloudcdn.owcontent.com/games/turbogames/turboplinko.png?221746631283000" },
    { "name": "Turbo Mines", "image": "https://cloudcdn.owcontent.com/games/turbogames/turbomines.png?221746631283000" },
    { "name": "Hamsta", "image": "https://cloudcdn.owcontent.com/games/turbogames/hamsta.png?221746631283000" },
    { "name": "PLINKO", "image": "https://cloudcdn.owcontent.com/games/exagaming/plinko.png?221729511420000" },
    { "name": "ROULETTE", "image": "https://cloudcdn.owcontent.com/games/exagaming/roulette.png?221729511443000" },
    { "name": "MINE", "image": "https://cloudcdn.owcontent.com/games/exagaming/mine.png?221729511459000" },
    { "name": "BLACKJACK", "image": "https://cloudcdn.owcontent.com/games/exagaming/black-jack.jpg?221729511507000" },
    { "name": "Plinko", "image": "https://cloudcdn.owcontent.com/games/betsolutions/plinko.jpg?221596007900000" },
    { "name": "Shell", "image": "https://cloudcdn.owcontent.com/games/falcon/shell.png?221656834108000" },
    { "name": "Wicket Blast", "image": "https://cloudcdn.owcontent.com/games//turbogames/wicketblast.png?221746631283000" },
    { "name": "Trading Dice", "image": "https://cloudcdn.owcontent.com/games//turbogames/tradingdice.png?221746631283000" },
    { "name": "Magic Keno", "image": "https://cloudcdn.owcontent.com/games/turbogames/keno.png?221746631283000" },
    { "name": "Save the Princess", "image": "https://cloudcdn.owcontent.com/games/turbogames/stp.png?221746631283000" },
    { "name": "Dogs' Street", "image": "https://cloudcdn.owcontent.com/games/turbogames/dogstreet.png?221746631283000" },
    { "name": "JavelinX", "image": "https://cloudcdn.owcontent.com/games/turbogames/javelinx.png?221746631283000" },
    { "name": "Bayraktar", "image": "https://cloudcdn.owcontent.com/games/turbogames/bayraktar.png?221746631283000" },
    { "name": "Limbo Rider", "image": "https://cloudcdn.owcontent.com/games/turbogames/limbo.png?221746631283000" },
    { "name": "Ball & Ball", "image": "https://cloudcdn.owcontent.com/games/turbogames/ballandball.png?221746631283000" },
    { "name": "Fury Stairs", "image": "https://cloudcdn.owcontent.com/games/turbogames/stairs.png?221746631283000" },
    { "name": "Towers", "image": "https://cloudcdn.owcontent.com/games/turbogames/towers.png?221746631283000" },
    { "name": "Neko", "image": "https://cloudcdn.owcontent.com/games/turbogames/neko.png?221746631283000" },
    { "name": "Mines", "image": "https://cloudcdn.owcontent.com/games/turbogames/mines.png?221746631283000" },
    { "name": "Dice Twice", "image": "https://cloudcdn.owcontent.com/games/turbogames/dice.png?221746631283000" },
    { "name": "Burning Ice 40", "image": "https://cloudcdn.owcontent.com/games/smartsoft/BlazingHot40.jpg?221630054651000" },
    { "name": "Burning Ice 10", "image": "https://cloudcdn.owcontent.com/games/smartsoft/BlazingHot10.jpg?221630054647000" },
    { "name": "Burning Ice", "image": "https://cloudcdn.owcontent.com/games/smartsoft/BlazingHot.jpg?221630054641000" },
    { "name": "Samurai", "image": "https://cloudcdn.owcontent.com/games/smartsoft/Samurai.jpg?221630054627000" },
    { "name": "Virtual Classic Roulette", "image": "https://cloudcdn.owcontent.com/games/smartsoft/VirtualClassicRoulette.jpg?221631526834000" },
    { "name": "Virtual Burning Roulette", "image": "https://cloudcdn.owcontent.com/games/smartsoft/VirtualBurningRoulette.jpg?221631526826000" },
    { "name": "Virtual Roulette", "image": "https://cloudcdn.owcontent.com/games/smartsoft/VirtualRoulette.jpg?221631526823000" },
    { "name": "Russian Keno", "image": "https://cloudcdn.owcontent.com/games/smartsoft/RussianKeno.jpg?221631526887000" },
    { "name": "Soccer Crash", "image": "https://cloudcdn.owcontent.com/games/studio21/s21.crash.soccer.gif?221726221975000" },
    { "name": "Cricket Crash", "image": "https://cloudcdn.owcontent.com/games/studio21/s21.crash.cricket.gif?221726221976000" },
    { "name": "IPL Cricket Crash", "image": "https://cloudcdn.owcontent.com/games/studio21/s21.crash.cricket.ipl.gif?221726221978000" },
    { "name": "Alien Abduction", "image": "https://cloudcdn.owcontent.com/games/studio21/s21.crash.alien.gif?221726221979000" },
    { "name": "Pirate vs. Parrot", "image": "https://cloudcdn.owcontent.com/games/studio21/s21.coin.flip.pvp.gif?221726221979000" },
    { "name": "Venus Flytrap", "image": "https://cloudcdn.owcontent.com/games/studio21/s21.crash.venus.gif?221726221980000" },
    { "name": "Sammy The Sloth", "image": "https://cloudcdn.owcontent.com/games/studio21/s21.crash.sammy.gif?221726221981000" },
    { "name": "Olympic Javelin", "image": "https://cloudcdn.owcontent.com/games/studio21/s21.crash.javelin.gif?221726221982000" },
    { "name": "Multi Hot Ways", "image": "https://cloudcdn.owcontent.com/games/smartsoft/MultiHotWays.webp?221691475574000" },
    { "name": "MineIsland", "image": "https://cloudcdn.owcontent.com/games/smartsoft/MineIsland.jpg?221744022818000" },
    { "name": "RollX", "image": "https://cloudcdn.owcontent.com/games/smartsoft/RollX.jpg?221744022846000" },
    { "name": "Smash X", "image": "https://cloudcdn.owcontent.com/games/smartsoft/SmashX.jpg?221744023818000" },
    { "name": "HunterX", "image": "https://cloudcdn.owcontent.com/games/smartsoft/HunterX.jpg?221744022957000" },
    { "name": "Crazy HuntX", "image": "https://cloudcdn.owcontent.com/games/smartsoft/CrazyHuntX.png?221744025736000" },
    { "name": "Crash Duel X", "image": "https://cloudcdn.owcontent.com/games/smartsoft/TugOfWar.jpg?221744023051000" },
    { "name": "Wild & Gods", "image": "https://cloudcdn.owcontent.com/games/smartsoft/WildsAndGods.jpg?221744023096000" },
    { "name": "Book of Futuria", "image": "https://cloudcdn.owcontent.com/games/smartsoft/BookOfFuturia.jpg?221744023132000" },
    { "name": "WildMultiStar", "image": "https://cloudcdn.owcontent.com/games/smartsoft/WildMultiStar.jpg?221744025809000" },
    { "name": "HotSamba", "image": "https://cloudcdn.owcontent.com/games/smartsoft/HotSamba.jpg?221744023855000" },
    { "name": "Vampires", "image": "https://cloudcdn.owcontent.com/games/smartsoft/Vampires.jpg?221744023218000" },
    { "name": "Wild Jungle", "image": "https://cloudcdn.owcontent.com/games/smartsoft/Jungles.jpg?221744023309000" },
    { "name": "Foxy Hot 20", "image": "https://cloudcdn.owcontent.com/games/smartsoft/FoxyHot20.jpg?221744023394000" },
    { "name": "Safari Simba", "image": "https://cloudcdn.owcontent.com/games/smartsoft/SafariSimba.jpg?221744023449000" },
    { "name": "Sugar Fiesta", "image": "https://cloudcdn.owcontent.com/games/smartsoft/SugarFiesta.jpg?221744023483000" },
    { "name": "DoubleX", "image": "https://cloudcdn.owcontent.com/games/smartsoft/SlicerX.jpg?221744025771000" },
    { "name": "CricketX", "image": "https://cloudcdn.owcontent.com/games/smartsoft/CricketX.jpg?221744022988000" },
    { "name": "Take My Plinko", "image": "https://cloudcdn.owcontent.com/games/turbogames/takemyplinko.png?221746631283000" },
    { "name": "Fast Fielder", "image": "https://cloudcdn.owcontent.com/games/turbogames/fastfielder.png?221746631283000" },
    { "name": "Bubbles", "image": "https://cloudcdn.owcontent.com/games/turbogames/bubbles.png?221746631283000" },
    { "name": "Double Roll", "image": "https://cloudcdn.owcontent.com/games/turbogames/doubleroll.png?221694323795000" },
    { "name": "Spin Strike", "image": "https://cloudcdn.owcontent.com/games/turbogames/spinstrike.png?221746631283000" },
    { "name": "Hi-Lo", "image": "https://cloudcdn.owcontent.com/games/turbogames/hilo.png?221746631283000" },
    { "name": "RodeoX", "image": "https://cloudcdn.owcontent.com/games/smartsoft/RodeoX.webp?221745488167000" },
    { "name": "Dracula's Fortune", "image": "https://cloudcdn.owcontent.com/games/smartsoft/DraculasFortune.webp?221745488184000" },
    { "name": "Samba Da Deausa", "image": "https://cloudcdn.owcontent.com/games/smartsoft/FortuneCarnivalBonanza.webp?221745488202000" },
    { "name": "Book Of Bonanza", "image": "https://cloudcdn.owcontent.com/games/smartsoft/BookOfBonanza.webp?221745488217000" },
    { "name": "Mad Slot", "image": "https://cloudcdn.owcontent.com/games/smartsoft/MadSlot.webp?221745488233000" },
    { "name": "BaoSlot5X", "image": "https://cloudcdn.owcontent.com/games/smartsoft/BaoSlot5X.webp?221745488250000" },
    { "name": "Habesha Fortune 5", "image": "https://cloudcdn.owcontent.com/games/smartsoft/HabeshaFortune5.webp?221745488266000" },
    { "name": "Jungle Sisters", "image": "https://cloudcdn.owcontent.com/games/smartsoft/JungleSisters.webp?221745488279000" }
]